rtv/__init__.py
rtv/__version__.py
rtv/cli.py
rtv/exceptions.py
rtv/onetab.py
rtv/options.py
rtv/rtvdownloader.py
rtv/utils.py
rtv/video.py
rtv/downloaders/__init__.py
rtv/downloaders/common.py
rtv/downloaders/youtubedl.py
rtv/extractors/__init__.py
rtv/extractors/common.py
rtv/extractors/ipla.py
rtv/extractors/polsatnews.py
rtv/extractors/polskieradio.py
rtv/extractors/radiozet.py
rtv/extractors/rmf24.py
rtv/extractors/tokfm.py
rtv/extractors/tvn24.py
rtv/extractors/tvpinfo.py
rtv/extractors/tvpparlament.py
rtv/extractors/vod.py
rtv/extractors/vodtvp.py
rtv/extractors/wp.py
rtv_downloader-2.0.6.dist-info/METADATA
rtv_downloader-2.0.6.dist-info/RECORD
rtv_downloader-2.0.6.dist-info/WHEEL
rtv_downloader-2.0.6.dist-info/entry_points.txt
rtv_downloader-2.0.6.dist-info/top_level.txt
